ParseGenius/ParseGenius.py
ParseGenius/__init__.py
pdf_parser_engine/__init__.py
pdf_parser_engine/pdf_parser_engine.py
tests/__init__.py
tests/test_parser.py
ParseGenius-0.1.2.dist-info/METADATA
ParseGenius-0.1.2.dist-info/WHEEL
ParseGenius-0.1.2.dist-info/top_level.txt
ParseGenius-0.1.2.dist-info/RECORD
