Metadata-Version: 2.1
Name: ParseGenius
Version: 0.1.2
Summary: A text-in parser engine for pdf to markdown processing
Home-page: https://github.com/intsig/x2md_tools/python/ParseGenius_engine
Author: doughboii
License: UNKNOWN
Platform: UNKNOWN
Classifier: Programming Language :: Python :: 3
Classifier: License :: OSI Approved :: MIT License
Classifier: Operating System :: OS Independent
Requires-Python: >=3.6
Requires-Dist: opencv-python-headless
Requires-Dist: numpy
